{
  "jsonrpc": "2.0",
  "result": {
    "slot": 374559395,
    "transaction": {
      "signatures": [
        "amnKrKQAhrNEYrEGoiTPAG83XoUCgsPXbxxTk7xrA63UwUsaeippPyjVmM4cy217MtHfK8Bnw36s4A6PwncxSr1"
      ],
      "message": {
        "header": {
          "numRequiredSignatures": 1,
          "numReadonlySignedAccounts": 0,
          "numReadonlyUnsignedAccounts": 4
        },
        "accountKeys": [
          "HeDpLVZDrsG3UeoBff86cw2S8CgTJNdWNgqafqaprmFN",
          "6iBZxy8Nf7c3jjWsVL7z36BsfTsJnhhmY6odYfTyTKxT",
          "9fqjtzTtfwBp9Y3R69piqY6eaQiZGT86NEtnNLJo3pZD",
          "JBcgFeRXnKXYta1ZoKfen2qgNy9pj9rUu41oR2bqcjPQ",
          "11111111111111111111111111111111",
          "ComputeBudget111111111111111111111111111111",
          "JUP6LkbZbjS1jKKwapdHNy74zcZ3tLUZoi5QNyVTaV4",
          "jitodontfront1111111111111111JustUseJupiter"
        ],
        "recentBlockhash": "CP3yoXm7fzdnstTYYHXGmYWX6NiZvKY6CtbUkzZxbF5c",
        "instructions": [
          {
            "programIdIndex": 5,
            "accounts": [],
            "data": "EnB2nj",
            "stackHeight": 1
          },
          {
            "programIdIndex": 5,
            "accounts": [],
            "data": "3DTZbgwsozUF",
            "stackHeight": 1
          },
          {
            "programIdIndex": 6,
            "accounts": [
              18,
              0,
              2,
              1,
              6,
              15,
              6,
              21,
              6,
              20,
              0,
              9,
              12,
              10,
              1,
              2,
              17,
              18,
              16,
              14,
              0,
              8,
              19,
              23,
              11,
              13,
              1,
              2,
              15,
              22,
              18,
              18,
              16,
              7
            ],
            "data": "e6M8XkMMy3Dbrn8aiiNCVpJyxW5QSDfuWtDpjwnMtV1vm9iR45MPDPR6Ms8C5SpphE7",
            "stackHeight": 1
          },
          {
            "programIdIndex": 4,
            "accounts": [
              0,
              3
            ],
            "data": "3Bxs44yZDABxZymy",
            "stackHeight": 1
          }
        ],
        "addressTableLookups": [
          {
            "accountKey": "Bio8NY8ZZ1kwWk7BHownvBEAQjBDS8xX98T5ei4ZpW9b",
            "writableIndexes": [
              154,
              123,
              124,
              156,
              125,
              155
            ],
            "readonlyIndexes": [
              161,
              1,
              133,
              136,
              132,
              157,
              116,
              61,
              0,
              158
            ]
          }
        ]
      }
    },
    "meta": {
      "err": null,
      "status": {
        "Ok": null
      },
      "fee": 5000,
      "preBalances": [
        92109869,
        9537553,
        2039280,
        0,
        1,
        1,
        2729681025,
        0,
        34987980,
        12934430,
        2044300,
        17633336710708,
        2932495709539,
        2039282,
        1141441,
        1176024750681,
        0,
        1169280,
        5299606121,
        2060161,
        1141546,
        3596047,
        419233326820,
        7298979843
      ],
      "postBalances": [
        90949773,
        9537553,
        2039280,
        1155096,
        1,
        1,
        2729681025,
        0,
        34987980,
        12934430,
        2044300,
        17648878723344,
        2916953696903,
        2039282,
        1141441,
        1176024750681,
        0,
        1169280,
        5299606121,
        2060161,
        1141546,
        3596047,
        419233326820,
        7298979843
      ],
      "innerInstructions": [
        {
          "index": 2,
          "instructions": [
            {
              "programIdIndex": 20,
              "accounts": [
                0,
                9,
                12,
                10,
                1,
                2,
                17,
                18,
                16
              ],
              "data": "iN9UF8SEiPvHMv8VAXbFDwWKr1HjhsWrAg",
              "stackHeight": 2
            },
            {
              "programIdIndex": 18,
              "accounts": [
                12,
                1,
                9
              ],
              "data": "3rJf4RUBKukb",
              "stackHeight": 3
            },
            {
              "programIdIndex": 18,
              "accounts": [
                2,
                10,
                0
              ],
              "data": "3d7gCuyVnWRu",
              "stackHeight": 3
            },
            {
              "programIdIndex": 6,
              "accounts": [
                21
              ],
              "data": "QMqFu4fYGGeUEysFnenhAvZyPm1JAod68DeKDsNFkksrnYHJ8XaBvc9KfAkZJppLvfZWescnBDy7XXrvLVt6U99zvf8VBvqZNxdQqvUn2iQ5GrfLMrNf8SCzbyQx7KX11zZp4oTLeY88bNDaBcpSmc8XUtEKU4yGr7CZHkK5cj7cwaP",
              "stackHeight": 2
            },
            {
              "programIdIndex": 14,
              "accounts": [
                0,
                8,
                19,
                23,
                11,
                13,
                1,
                2,
                15,
                22,
                18,
                18,
                16
              ],
              "data": "KumUK1K6ZZbZVrsKmSEys7x3",
              "stackHeight": 2
            },
            {
              "programIdIndex": 18,
              "accounts": [
                1,
                11,
                0
              ],
              "data": "3rJf4RUBKukb",
              "stackHeight": 3
            },
            {
              "programIdIndex": 18,
              "accounts": [
                13,
                2,
                8
              ],
              "data": "3S3A99EKZoFV",
              "stackHeight": 3
            },
            {
              "programIdIndex": 6,
              "accounts": [
                21
              ],
              "data": "QMqFu4fYGGeUEysFnenhAvC7BGCuDcTCztRgxLjW5B9gLiCQPTsQY7PkLQRQvJvaSE47mzytBJRPT6QefcLWwNy72dbFzHFKs81DYdsKthbsYQ4WuqPJcPmNrStxdRFzqNP3ZBeoszha8g1Y66ZURHheUofL8fjcgdUunGjTVt2oR7d",
              "stackHeight": 2
            }
          ]
        }
      ],
      "logMessages": [
        "Program ComputeBudget111111111111111111111111111111 invoke [1]",
        "Program ComputeBudget111111111111111111111111111111 success",
        "Program ComputeBudget111111111111111111111111111111 invoke [1]",
        "Program ComputeBudget111111111111111111111111111111 success",
        "Program JUP6LkbZbjS1jKKwapdHNy74zcZ3tLUZoi5QNyVTaV4 invoke [1]",
        "Program log: Instruction: Route",
        "Program 9H6tua7jkLhdm3w8BvgpTn5LZNU7g4ZynDmCiNN3q6Rp invoke [2]",
        "Program log: \ud83d\udc1f",
        "Program TokenkegQfeZyiNwAJbNbGKPFXCWuBvf9Ss623VQ5DA invoke [3]",
        "Program log: Instruction: Transfer",
        "Program TokenkegQfeZyiNwAJbNbGKPFXCWuBvf9Ss623VQ5DA consumed 4736 of 106545 compute units",
        "Program TokenkegQfeZyiNwAJbNbGKPFXCWuBvf9Ss623VQ5DA success",
        "Program TokenkegQfeZyiNwAJbNbGKPFXCWuBvf9Ss623VQ5DA invoke [3]",
        "Program log: Instruction: Transfer",
        "Program TokenkegQfeZyiNwAJbNbGKPFXCWuBvf9Ss623VQ5DA consumed 4645 of 100645 compute units",
        "Program TokenkegQfeZyiNwAJbNbGKPFXCWuBvf9Ss623VQ5DA success",
        "Program data: fLMtskd1eEUIWEkw/3gd9Y2SDLRYLYqFaDXZpZJ2D0baK/x3enb6Yi7W2tf8zGxd24leMK01tPh/UYujPW7UOEUKp5Q6jO/Vv5UvDS6eN94wSzulVKGgC/xW3GTCeByOgWtRMH78x2t9mKcEx0+H2l804ruYvH+6HFAqZ4NXRe7FsULi44sNVkN7vUR2RfKpTx5R95FdWO+Y8MZnn1dZ79FzfoLgkKEQYQ8/mGaooBCd8MNnmldc75zwwmebV13vosTzoT5VUu9wGteW/ldT7026r/mVV1DvHZ8e1ZdXUe9ZEPxnClZW737zyGeRV1fvlfDLZ5JXVO+V8Mpnk1dV7w==",
        "Program 9H6tua7jkLhdm3w8BvgpTn5LZNU7g4ZynDmCiNN3q6Rp consumed 34333 of 129515 compute units",
        "Program 9H6tua7jkLhdm3w8BvgpTn5LZNU7g4ZynDmCiNN3q6Rp success",
        "Program JUP6LkbZbjS1jKKwapdHNy74zcZ3tLUZoi5QNyVTaV4 invoke [2]",
        "Program JUP6LkbZbjS1jKKwapdHNy74zcZ3tLUZoi5QNyVTaV4 consumed 199 of 93563 compute units",
        "Program JUP6LkbZbjS1jKKwapdHNy74zcZ3tLUZoi5QNyVTaV4 success",
        "Program SV2EYYJyRz2YhfXwXnhNAevDEui5Q6yrfyo13WtupPF invoke [2]",
        "Program data: S3VCwUhV8CXSyrcV3EtPUNCsQJvXpBqCGUobEJZVRnl81GUAAAAAAKFSUxYAAAAAAAAAAAAAAAAAAAAAAAAAAA==",
        "Program TokenkegQfeZyiNwAJbNbGKPFXCWuBvf9Ss623VQ5DA invoke [3]",
        "Program log: Instruction: Transfer",
        "Program TokenkegQfeZyiNwAJbNbGKPFXCWuBvf9Ss623VQ5DA consumed 4736 of 28390 compute units",
        "Program TokenkegQfeZyiNwAJbNbGKPFXCWuBvf9Ss623VQ5DA success",
        "Program TokenkegQfeZyiNwAJbNbGKPFXCWuBvf9Ss623VQ5DA invoke [3]",
        "Program log: Instruction: Transfer",
        "Program TokenkegQfeZyiNwAJbNbGKPFXCWuBvf9Ss623VQ5DA consumed 4645 of 22233 compute units",
        "Program TokenkegQfeZyiNwAJbNbGKPFXCWuBvf9Ss623VQ5DA success",
        "Program SV2EYYJyRz2YhfXwXnhNAevDEui5Q6yrfyo13WtupPF consumed 70436 of 86248 compute units",
        "Program SV2EYYJyRz2YhfXwXnhNAevDEui5Q6yrfyo13WtupPF success",
        "Program JUP6LkbZbjS1jKKwapdHNy74zcZ3tLUZoi5QNyVTaV4 invoke [2]",
        "Program JUP6LkbZbjS1jKKwapdHNy74zcZ3tLUZoi5QNyVTaV4 consumed 199 of 14188 compute units",
        "Program JUP6LkbZbjS1jKKwapdHNy74zcZ3tLUZoi5QNyVTaV4 success",
        "Program JUP6LkbZbjS1jKKwapdHNy74zcZ3tLUZoi5QNyVTaV4 consumed 121680 of 134383 compute units",
        "Program return: JUP6LkbZbjS1jKKwapdHNy74zcZ3tLUZoi5QNyVTaV4 SzTRsgAAAAA=",
        "Program JUP6LkbZbjS1jKKwapdHNy74zcZ3tLUZoi5QNyVTaV4 success",
        "Program 11111111111111111111111111111111 invoke [1]",
        "Program 11111111111111111111111111111111 success"
      ],
      "preTokenBalances": [
        {
          "accountIndex": 1,
          "mint": "So11111111111111111111111111111111111111112",
          "uiTokenAmount": {
            "uiAmount": 0.007498273,
            "decimals": 9,
            "amount": "7498273",
            "uiAmountString": "0.007498273"
          },
          "owner": "HeDpLVZDrsG3UeoBff86cw2S8CgTJNdWNgqafqaprmFN",
          "programId": "TokenkegQfeZyiNwAJbNbGKPFXCWuBvf9Ss623VQ5DA"
        },
        {
          "accountIndex": 2,
          "mint": "EPjFWdd5AufqSSqeM2qN1xzybapC8G4wEGGkZwyTDt1v",
          "uiTokenAmount": {
            "uiAmount": 22253.900752,
            "decimals": 6,
            "amount": "22253900752",
            "uiAmountString": "22253.900752"
          },
          "owner": "HeDpLVZDrsG3UeoBff86cw2S8CgTJNdWNgqafqaprmFN",
          "programId": "TokenkegQfeZyiNwAJbNbGKPFXCWuBvf9Ss623VQ5DA"
        },
        {
          "accountIndex": 10,
          "mint": "EPjFWdd5AufqSSqeM2qN1xzybapC8G4wEGGkZwyTDt1v",
          "uiTokenAmount": {
            "uiAmount": 463606.63933,
            "decimals": 6,
            "amount": "463606639330",
            "uiAmountString": "463606.63933"
          },
          "owner": "6n9VhCwQ7EwK6NqFDjnHPzEk6wZdRBTfh43RFgHQWHuQ",
          "programId": "TokenkegQfeZyiNwAJbNbGKPFXCWuBvf9Ss623VQ5DA"
        },
        {
          "accountIndex": 11,
          "mint": "So11111111111111111111111111111111111111112",
          "uiTokenAmount": {
            "uiAmount": 17633.334661426,
            "decimals": 9,
            "amount": "17633334661426",
            "uiAmountString": "17633.334661426"
          },
          "owner": "65ZHSArs5XxPseKQbB1B4r16vDxMWnCxHMzogDAqiDUc",
          "programId": "TokenkegQfeZyiNwAJbNbGKPFXCWuBvf9Ss623VQ5DA"
        },
        {
          "accountIndex": 12,
          "mint": "So11111111111111111111111111111111111111112",
          "uiTokenAmount": {
            "uiAmount": 2932.493661233,
            "decimals": 9,
            "amount": "2932493661233",
            "uiAmountString": "2932.493661233"
          },
          "owner": "6n9VhCwQ7EwK6NqFDjnHPzEk6wZdRBTfh43RFgHQWHuQ",
          "programId": "TokenkegQfeZyiNwAJbNbGKPFXCWuBvf9Ss623VQ5DA"
        },
        {
          "accountIndex": 13,
          "mint": "EPjFWdd5AufqSSqeM2qN1xzybapC8G4wEGGkZwyTDt1v",
          "uiTokenAmount": {
            "uiAmount": 3299973.245586,
            "decimals": 6,
            "amount": "3299973245586",
            "uiAmountString": "3299973.245586"
          },
          "owner": "65ZHSArs5XxPseKQbB1B4r16vDxMWnCxHMzogDAqiDUc",
          "programId": "TokenkegQfeZyiNwAJbNbGKPFXCWuBvf9Ss623VQ5DA"
        }
      ],
      "postTokenBalances": [
        {
          "accountIndex": 1,
          "mint": "So11111111111111111111111111111111111111112",
          "uiTokenAmount": {
            "uiAmount": 0.007498273,
            "decimals": 9,
            "amount": "7498273",
            "uiAmountString": "0.007498273"
          },
          "owner": "HeDpLVZDrsG3UeoBff86cw2S8CgTJNdWNgqafqaprmFN",
          "programId": "TokenkegQfeZyiNwAJbNbGKPFXCWuBvf9Ss623VQ5DA"
        },
        {
          "accountIndex": 2,
          "mint": "EPjFWdd5AufqSSqeM2qN1xzybapC8G4wEGGkZwyTDt1v",
          "uiTokenAmount": {
            "uiAmount": 22253.951118,
            "decimals": 6,
            "amount": "22253951118",
            "uiAmountString": "22253.951118"
          },
          "owner": "HeDpLVZDrsG3UeoBff86cw2S8CgTJNdWNgqafqaprmFN",
          "programId": "TokenkegQfeZyiNwAJbNbGKPFXCWuBvf9Ss623VQ5DA"
        },
        {
          "accountIndex": 10,
          "mint": "EPjFWdd5AufqSSqeM2qN1xzybapC8G4wEGGkZwyTDt1v",
          "uiTokenAmount": {
            "uiAmount": 466606.643823,
            "decimals": 6,
            "amount": "466606643823",
            "uiAmountString": "466606.643823"
          },
          "owner": "6n9VhCwQ7EwK6NqFDjnHPzEk6wZdRBTfh43RFgHQWHuQ",
          "programId": "TokenkegQfeZyiNwAJbNbGKPFXCWuBvf9Ss623VQ5DA"
        },
        {
          "accountIndex": 11,
          "mint": "So11111111111111111111111111111111111111112",
          "uiTokenAmount": {
            "uiAmount": 17648.876674062,
            "decimals": 9,
            "amount": "17648876674062",
            "uiAmountString": "17648.876674062"
          },
          "owner": "65ZHSArs5XxPseKQbB1B4r16vDxMWnCxHMzogDAqiDUc",
          "programId": "TokenkegQfeZyiNwAJbNbGKPFXCWuBvf9Ss623VQ5DA"
        },
        {
          "accountIndex": 12,
          "mint": "So11111111111111111111111111111111111111112",
          "uiTokenAmount": {
            "uiAmount": 2916.951648597,
            "decimals": 9,
            "amount": "2916951648597",
            "uiAmountString": "2916.951648597"
          },
          "owner": "6n9VhCwQ7EwK6NqFDjnHPzEk6wZdRBTfh43RFgHQWHuQ",
          "programId": "TokenkegQfeZyiNwAJbNbGKPFXCWuBvf9Ss623VQ5DA"
        },
        {
          "accountIndex": 13,
          "mint": "EPjFWdd5AufqSSqeM2qN1xzybapC8G4wEGGkZwyTDt1v",
          "uiTokenAmount": {
            "uiAmount": 3296973.190727,
            "decimals": 6,
            "amount": "3296973190727",
            "uiAmountString": "3296973.190727"
          },
          "owner": "65ZHSArs5XxPseKQbB1B4r16vDxMWnCxHMzogDAqiDUc",
          "programId": "TokenkegQfeZyiNwAJbNbGKPFXCWuBvf9Ss623VQ5DA"
        }
      ],
      "rewards": [],
      "loadedAddresses": {
        "writable": [
          "65ZHSArs5XxPseKQbB1B4r16vDxMWnCxHMzogDAqiDUc",
          "6n9VhCwQ7EwK6NqFDjnHPzEk6wZdRBTfh43RFgHQWHuQ",
          "7Rf8Gu8YemSoGjZT3z1cL5BT9HLbGywcyaz8Mrbhd1MH",
          "CRo8DBwrmd97DJfAnvCv96tZPL5Mktf2NZy2ZnhDer1A",
          "Cv9St5tDTGwpbG5UVvM6QvFmf3FYSXc14W9BYvQN5wAZ",
          "GhFfLFSprPpfoRaWakPMmJTMJBHuz6C694jYwxy2dAic"
        ],
        "readonly": [
          "SV2EYYJyRz2YhfXwXnhNAevDEui5Q6yrfyo13WtupPF",
          "So11111111111111111111111111111111111111112",
          "Sysvar1nstructions1111111111111111111111111",
          "SysvarC1ock11111111111111111111111111111111",
          "TokenkegQfeZyiNwAJbNbGKPFXCWuBvf9Ss623VQ5DA",
          "2ny7eGyZCoeEVTkNLf5HcnJFBKkyA4p4gcrtb3b8y8ou",
          "9H6tua7jkLhdm3w8BvgpTn5LZNU7g4ZynDmCiNN3q6Rp",
          "D8cy77BBepLMngZx6ZukaTff5hCt1HrWyKk3Hnd9oitf",
          "EPjFWdd5AufqSSqeM2qN1xzybapC8G4wEGGkZwyTDt1v",
          "FmxXDSR9WvpJTCh738D1LEDuhMoA8geCtZgHb3isy7Dp"
        ]
      },
      "computeUnitsConsumed": 122130
    },
    "version": 0,
    "blockTime": 1760940122
  },
  "id": 1,
  "signature": "amnKrKQAhrNEYrEGoiTPAG83XoUCgsPXbxxTk7xrA63UwUsaeippPyjVmM4cy217MtHfK8Bnw36s4A6PwncxSr1"
}